cannerflow/__init__.py
cannerflow/client.py
cannerflow/constants.py
cannerflow/csv_wrapper.py
cannerflow/cursor.py
cannerflow/exceptions.py
cannerflow/file.py
cannerflow/image_wrapper.py
cannerflow/json_wrapper.py
cannerflow/logging.py
cannerflow/query.py
cannerflow/request.py
cannerflow/saved_query.py
cannerflow/utils.py
cannerflow/workspace.py
cannerflow_python_client_development-0.9.0.dist-info/LICENSE
cannerflow_python_client_development-0.9.0.dist-info/METADATA
cannerflow_python_client_development-0.9.0.dist-info/WHEEL
cannerflow_python_client_development-0.9.0.dist-info/top_level.txt
cannerflow_python_client_development-0.9.0.dist-info/RECORD
